topsis_101703445/cli.py
topsis_101703445/topsis.py
topsis_101703445-1.0.1.dist-info/LICENSE.txt
topsis_101703445-1.0.1.dist-info/METADATA
topsis_101703445-1.0.1.dist-info/WHEEL
topsis_101703445-1.0.1.dist-info/entry_points.txt
topsis_101703445-1.0.1.dist-info/top_level.txt
topsis_101703445-1.0.1.dist-info/RECORD
