Metadata-Version: 2.1
Name: topsis-101703445
Version: 1.0.1
Summary: A python package implementing topsis
Home-page: UNKNOWN
Author: Ritwik Khurana
Author-email: UNKNOWN
License: MIT
Platform: UNKNOWN
Classifier: License :: OSI Approved :: MIT License
Classifier: Programming Language :: Python :: 3
Classifier: Programming Language :: Python :: 3.7
